numerical_methods/__init__.py
numerical_methods/methods.py
numerical_methods-0.1.0.dist-info/LICENSE
numerical_methods-0.1.0.dist-info/METADATA
numerical_methods-0.1.0.dist-info/WHEEL
numerical_methods-0.1.0.dist-info/top_level.txt
numerical_methods-0.1.0.dist-info/RECORD
