Metadata-Version: 2.1
Name: numerical-methods
Version: 0.1.0
Summary: Library for solving mathematical problems in numerical form
Home-page: https://d1mka.fun
Author: Dimka-Lab
Author-email: alexeew.di@gmail.com
License: MIT
Platform: UNKNOWN
Classifier: Intended Audience :: Developers
Classifier: License :: OSI Approved :: MIT License
Classifier: Programming Language :: Python
Classifier: Programming Language :: Python :: 3
Classifier: Programming Language :: Python :: 3.6
Classifier: Programming Language :: Python :: 3.7
Classifier: Programming Language :: Python :: 3.8
Classifier: Programming Language :: Python :: 3.9
Classifier: Operating System :: OS Independent
Requires-Dist: numpy
